src/sum1bcc.v
module sum1bcc (A, B, Ci,Cout,S);

  input  A;
  input  B;
  input  Ci;
  output Cout;
  output S;

  reg [1:0] st;  
  assign S = st[0];
  assign Cout = st[1];

  always @ ( * ) begin
  	st  = 	A+B+Ci;
  end
  
endmodule

src/sum1bcc_TB.v
`include "sum1bcc.v"
`timescale 1ns/1ns
module sum1bcc_TB;

  reg x;
  reg y;
  reg c;
  wire out;
  wire z;


sum1bcc uut(x, y, c,out,z);


initial begin
x=0; y=0; c=0; #3;
x=0; y=0; c=1; #3;
x=0; y=1; c=0; #3;
x=0; y=1; c=1; #3;
x=1; y=0; c=0; #3;
x=1; y=0; c=1; #3;
x=1; y=1; c=0; #3;
x=1; y=1; c=1; #3;



end

initial begin: TEST_CASE
     $dumpfile("sum1bcc_TB.vcd");
     $dumpvars(-1, uut);
     #(30) $finish;
   end

endmodule //

build/sum1bcc_TB.vcd
$date
	Tue Dec 03 14:19:43 2024
$end
$version
	Icarus Verilog
$end
$timescale
	1ns
$end
$scope module sum1bcc_TB $end
$scope module uut $end
$var wire 1 ! A $end
$var wire 1 " B $end
$var wire 1 # Ci $end
$var wire 1 $ S $end
$var wire 1 % Cout $end
$var reg 2 & st [1:0] $end
$upscope $end
$upscope $end
$enddefinitions $end
$comment Show the parameter values. $end
$dumpall
$end
#0
$dumpvars
b0 &
0%
0$
0#
0"
0!
$end
#3
1$
b1 &
1#
#6
0#
1"
#9
0$
1%
b10 &
1#
#12
1$
0%
b1 &
0#
0"
1!
#15
0$
1%
b10 &
1#
#18
0#
1"
#21
1$
b11 &
1#
